<?xml version="1.0" encoding="Windows-1252"?>
<!DOCTYPE POWERMART SYSTEM "powrmart.dtd">
<POWERMART CREATION_DATE="10/21/2025 20:02:16" REPOSITORY_VERSION="181.90">
<REPOSITORY NAME="REP_SVC_EDW_DEV_L2" VERSION="181" CODEPAGE="MS1252" DATABASETYPE="Oracle">
<FOLDER NAME="BRIQUELME" GROUP="" OWNER="admin" SHARED="NOTSHARED" DESCRIPTION="" PERMISSIONS="rwx---r--" UUID="2611647b-74a9-41d6-9c10-b35ffde5df0f">
    <SOURCE BUSINESSNAME ="" DATABASETYPE ="Flat File" DBDNAME ="FlatFile" DESCRIPTION ="" NAME ="dates" OBJECTVERSION ="1" OWNERNAME ="" VERSIONNUMBER ="1">
        <FLATFILE CODEPAGE ="MS1252" CONSECDELIMITERSASONE ="NO" DELIMITED ="YES" DELIMITERS ="," ESCAPE_CHARACTER ="" KEEPESCAPECHAR ="NO" LINESEQUENTIAL ="NO" MULTIDELIMITERSASAND ="YES" NULLCHARTYPE ="ASCII" NULL_CHARACTER ="*" PADBYTES ="1" QUOTE_CHARACTER ="DOUBLE" REPEATABLE ="NO" ROWDELIMITER ="0" SHIFTSENSITIVEDATA ="NO" SKIPROWS ="1" STRIPTRAILINGBLANKS ="NO"/>
        <TABLEATTRIBUTE NAME ="Base Table Name" VALUE =""/>
        <TABLEATTRIBUTE NAME ="Search Specification" VALUE =""/>
        <TABLEATTRIBUTE NAME ="Sort Specification" VALUE =""/>
        <TABLEATTRIBUTE NAME ="Datetime Format" VALUE ="A  19 mm/dd/yyyy hh24:mi:ss"/>
        <TABLEATTRIBUTE NAME ="Thousand Separator" VALUE ="None"/>
        <TABLEATTRIBUTE NAME ="Decimal Separator" VALUE ="."/>
        <TABLEATTRIBUTE NAME ="Add Currently Processed Flat File Name Port" VALUE ="NO"/>
        <SOURCEFIELD BUSINESSNAME ="" DATATYPE ="number" DESCRIPTION ="" FIELDNUMBER ="1" FIELDPROPERTY ="0" FIELDTYPE ="ELEMITEM" HIDDEN ="NO" KEYTYPE ="NOT A KEY" LENGTH ="7" LEVEL ="0" NAME ="DATE_ID" NULLABLE ="NULL" OCCURS ="0" OFFSET ="0" PHYSICALLENGTH ="7" PHYSICALOFFSET ="0" PICTURETEXT ="" PRECISION ="7" SCALE ="0" USAGE_FLAGS =""/>
        <SOURCEFIELD BUSINESSNAME ="" DATATYPE ="string" DESCRIPTION ="" FIELDNUMBER ="2" FIELDPROPERTY ="0" FIELDTYPE ="ELEMITEM" HIDDEN ="NO" KEYTYPE ="NOT A KEY" LENGTH ="10" LEVEL ="0" NAME ="DATE" NULLABLE ="NULL" OCCURS ="0" OFFSET ="7" PHYSICALLENGTH ="10" PHYSICALOFFSET ="7" PICTURETEXT ="" PRECISION ="10" SCALE ="0" USAGE_FLAGS =""/>
    </SOURCE>
    <TARGET BUSINESSNAME ="" CONSTRAINT ="" DATABASETYPE ="Oracle" DESCRIPTION ="" NAME ="STG_DATES" OBJECTVERSION ="1" TABLEOPTIONS ="" VERSIONNUMBER ="1">
        <TARGETFIELD BUSINESSNAME ="" DATATYPE ="number" DESCRIPTION ="" FIELDNUMBER ="1" KEYTYPE ="NOT A KEY" NAME ="DATE_ID_LEGACY" NULLABLE ="NULL" PICTURETEXT ="" PRECISION ="15" SCALE ="0"/>
        <TARGETFIELD BUSINESSNAME ="" DATATYPE ="varchar2" DESCRIPTION ="" FIELDNUMBER ="2" KEYTYPE ="NOT A KEY" NAME ="DATE_VALUE" NULLABLE ="NULL" PICTURETEXT ="" PRECISION ="29" SCALE ="0"/>
        <TARGETFIELD BUSINESSNAME ="" DATATYPE ="varchar2" DESCRIPTION ="" FIELDNUMBER ="3" KEYTYPE ="NOT A KEY" NAME ="DAY_OF_MONTH" NULLABLE ="NULL" PICTURETEXT ="" PRECISION ="20" SCALE ="0"/>
        <TARGETFIELD BUSINESSNAME ="" DATATYPE ="varchar2" DESCRIPTION ="" FIELDNUMBER ="4" KEYTYPE ="NOT A KEY" NAME ="MONTH_NUMBER" NULLABLE ="NULL" PICTURETEXT ="" PRECISION ="20" SCALE ="0"/>
        <TARGETFIELD BUSINESSNAME ="" DATATYPE ="varchar2" DESCRIPTION ="" FIELDNUMBER ="5" KEYTYPE ="NOT A KEY" NAME ="YEAR_VALUE" NULLABLE ="NULL" PICTURETEXT ="" PRECISION ="20" SCALE ="0"/>
        <TARGETFIELD BUSINESSNAME ="" DATATYPE ="varchar2" DESCRIPTION ="" FIELDNUMBER ="6" KEYTYPE ="NOT A KEY" NAME ="DAY_OF_WEEK" NULLABLE ="NULL" PICTURETEXT ="" PRECISION ="20" SCALE ="0"/>
        <TARGETFIELD BUSINESSNAME ="" DATATYPE ="varchar2" DESCRIPTION ="" FIELDNUMBER ="7" KEYTYPE ="NOT A KEY" NAME ="DAY_NAME" NULLABLE ="NULL" PICTURETEXT ="" PRECISION ="20" SCALE ="0"/>
        <TARGETFIELD BUSINESSNAME ="" DATATYPE ="varchar2" DESCRIPTION ="" FIELDNUMBER ="8" KEYTYPE ="NOT A KEY" NAME ="MONTH_NAME" NULLABLE ="NULL" PICTURETEXT ="" PRECISION ="20" SCALE ="0"/>
        <TARGETFIELD BUSINESSNAME ="" DATATYPE ="varchar2" DESCRIPTION ="" FIELDNUMBER ="9" KEYTYPE ="NOT A KEY" NAME ="DAY_OF_YEAR" NULLABLE ="NULL" PICTURETEXT ="" PRECISION ="20" SCALE ="0"/>
        <TARGETFIELD BUSINESSNAME ="" DATATYPE ="varchar2" DESCRIPTION ="" FIELDNUMBER ="10" KEYTYPE ="NOT A KEY" NAME ="MONTH_OF_YEAR" NULLABLE ="NULL" PICTURETEXT ="" PRECISION ="20" SCALE ="0"/>
        <TARGETFIELD BUSINESSNAME ="" DATATYPE ="varchar2" DESCRIPTION ="" FIELDNUMBER ="11" KEYTYPE ="NOT A KEY" NAME ="WEEK_OF_YEAR" NULLABLE ="NULL" PICTURETEXT ="" PRECISION ="20" SCALE ="0"/>
        <TARGETFIELD BUSINESSNAME ="" DATATYPE ="varchar2" DESCRIPTION ="" FIELDNUMBER ="12" KEYTYPE ="NOT A KEY" NAME ="DAY_OVERALL" NULLABLE ="NULL" PICTURETEXT ="" PRECISION ="20" SCALE ="0"/>
        <TARGETFIELD BUSINESSNAME ="" DATATYPE ="varchar2" DESCRIPTION ="" FIELDNUMBER ="13" KEYTYPE ="NOT A KEY" NAME ="WEEK_OVERALL" NULLABLE ="NULL" PICTURETEXT ="" PRECISION ="20" SCALE ="0"/>
        <TARGETFIELD BUSINESSNAME ="" DATATYPE ="varchar2" DESCRIPTION ="" FIELDNUMBER ="14" KEYTYPE ="NOT A KEY" NAME ="MONTH_OVERALL" NULLABLE ="NULL" PICTURETEXT ="" PRECISION ="20" SCALE ="0"/>
        <TARGETFIELD BUSINESSNAME ="" DATATYPE ="varchar2" DESCRIPTION ="" FIELDNUMBER ="15" KEYTYPE ="NOT A KEY" NAME ="YEAR_OVERALL" NULLABLE ="NULL" PICTURETEXT ="" PRECISION ="20" SCALE ="0"/>
        <TARGETFIELD BUSINESSNAME ="" DATATYPE ="varchar2" DESCRIPTION ="" FIELDNUMBER ="16" KEYTYPE ="NOT A KEY" NAME ="HOLIDAY_INDICATOR" NULLABLE ="NULL" PICTURETEXT ="" PRECISION ="20" SCALE ="0"/>
        <TARGETFIELD BUSINESSNAME ="" DATATYPE ="varchar2" DESCRIPTION ="" FIELDNUMBER ="17" KEYTYPE ="NOT A KEY" NAME ="WORKDAY_INDICATOR" NULLABLE ="NULL" PICTURETEXT ="" PRECISION ="20" SCALE ="0"/>
        <TARGETFIELD BUSINESSNAME ="" DATATYPE ="varchar2" DESCRIPTION ="" FIELDNUMBER ="18" KEYTYPE ="NOT A KEY" NAME ="WEEKDAY_INDICATOR" NULLABLE ="NULL" PICTURETEXT ="" PRECISION ="20" SCALE ="0"/>
        <TARGETFIELD BUSINESSNAME ="" DATATYPE ="varchar2" DESCRIPTION ="" FIELDNUMBER ="19" KEYTYPE ="NOT A KEY" NAME ="WEEKEND_INDICATOR" NULLABLE ="NULL" PICTURETEXT ="" PRECISION ="20" SCALE ="0"/>
        <TARGETFIELD BUSINESSNAME ="" DATATYPE ="varchar2" DESCRIPTION ="" FIELDNUMBER ="20" KEYTYPE ="NOT A KEY" NAME ="QUARTER_OF_YEAR" NULLABLE ="NULL" PICTURETEXT ="" PRECISION ="20" SCALE ="0"/>
        <TARGETFIELD BUSINESSNAME ="" DATATYPE ="varchar2" DESCRIPTION ="" FIELDNUMBER ="21" KEYTYPE ="NOT A KEY" NAME ="SEASON" NULLABLE ="NULL" PICTURETEXT ="" PRECISION ="20" SCALE ="0"/>
        <TARGETFIELD BUSINESSNAME ="" DATATYPE ="varchar2" DESCRIPTION ="" FIELDNUMBER ="22" KEYTYPE ="NOT A KEY" NAME ="LAST_DAY_IN_MONTH" NULLABLE ="NULL" PICTURETEXT ="" PRECISION ="20" SCALE ="0"/>
        <TARGETFIELD BUSINESSNAME ="" DATATYPE ="varchar2" DESCRIPTION ="" FIELDNUMBER ="23" KEYTYPE ="NOT A KEY" NAME ="LAST_DAY_IN_QUARTER" NULLABLE ="NULL" PICTURETEXT ="" PRECISION ="20" SCALE ="0"/>
        <TARGETFIELD BUSINESSNAME ="" DATATYPE ="varchar2" DESCRIPTION ="" FIELDNUMBER ="24" KEYTYPE ="NOT A KEY" NAME ="LAST_DAY_IN_YEAR" NULLABLE ="NULL" PICTURETEXT ="" PRECISION ="20" SCALE ="0"/>
    </TARGET>
    <TRANSFORMATION DESCRIPTION ="   " NAME ="re_exp_Stg_Dates" OBJECTVERSION ="1" REUSABLE ="YES" TYPE ="Expression" VERSIONNUMBER ="1">
        <TRANSFORMFIELD DATATYPE ="decimal" DEFAULTVALUE ="" DESCRIPTION ="" EXPRESSION ="DATE_ID" EXPRESSIONTYPE ="GENERAL" NAME ="DATE_ID" PICTURETEXT ="" PORTTYPE ="INPUT/OUTPUT" PRECISION ="7" SCALE ="0"/>
        <TRANSFORMFIELD DATATYPE ="string" DEFAULTVALUE ="" DESCRIPTION ="" NAME ="DATE" PICTURETEXT ="" PORTTYPE ="INPUT" PRECISION ="29" SCALE ="0"/>
        <TRANSFORMFIELD DATATYPE ="date/time" DEFAULTVALUE ="" DESCRIPTION ="" EXPRESSION ="TO_DATE(LTRIM(RTRIM(DATE)),&apos;MM/DD/YYYY&apos;)" EXPRESSIONTYPE ="GENERAL" NAME ="out_DATE_VALUE" PICTURETEXT ="" PORTTYPE ="LOCAL VARIABLE" PRECISION ="29" SCALE ="9"/>
        <TRANSFORMFIELD DATATYPE ="string" DEFAULTVALUE ="" DESCRIPTION =" " EXPRESSION ="GET_DATE_PART(out_DATE_VALUE,&apos;DD&apos;)" EXPRESSIONTYPE ="GENERAL" NAME ="var_DAY_OF_MONTH" PICTURETEXT ="" PORTTYPE ="LOCAL VARIABLE" PRECISION ="20" SCALE ="0"/>
        <TRANSFORMFIELD DATATYPE ="string" DEFAULTVALUE ="" DESCRIPTION ="" EXPRESSION ="GET_DATE_PART(out_DATE_VALUE,&apos;MM&apos;)" EXPRESSIONTYPE ="GENERAL" NAME ="var_MONTH_NUMBER" PICTURETEXT ="" PORTTYPE ="LOCAL VARIABLE" PRECISION ="20" SCALE ="0"/>
        <TRANSFORMFIELD DATATYPE ="string" DEFAULTVALUE ="" DESCRIPTION ="" EXPRESSION ="GET_DATE_PART(out_DATE_VALUE,&apos;Y&apos;)" EXPRESSIONTYPE ="GENERAL" NAME ="var_YEAR_VALUE" PICTURETEXT ="" PORTTYPE ="LOCAL VARIABLE" PRECISION ="20" SCALE ="0"/>
        <TRANSFORMFIELD DATATYPE ="string" DEFAULTVALUE ="" DESCRIPTION ="" EXPRESSION ="TO_CHAR(out_DATE_VALUE,&apos;DAY&apos;)" EXPRESSIONTYPE ="GENERAL" NAME ="var_DAY_NAME" PICTURETEXT ="" PORTTYPE ="LOCAL VARIABLE" PRECISION ="20" SCALE ="0"/>
        <TRANSFORMFIELD DATATYPE ="string" DEFAULTVALUE ="" DESCRIPTION ="" EXPRESSION ="DECODE (var_DAY_NAME&#xD;&#xA;,&apos;Monday&apos;,1&#xD;&#xA;,&apos;Tuesday&apos;,2&#xD;&#xA;,&apos;Wednesday&apos;,3&#xD;&#xA;,&apos;Thursday&apos;,4&#xD;&#xA;,&apos;Friday&apos;,5&#xD;&#xA;,&apos;Saturday&apos;,6&#xD;&#xA;,&apos;Sunday&apos;,7)" EXPRESSIONTYPE ="GENERAL" NAME ="var_DAY_OF_WEEK" PICTURETEXT ="" PORTTYPE ="LOCAL VARIABLE" PRECISION ="20" SCALE ="0"/>
        <TRANSFORMFIELD DATATYPE ="string" DEFAULTVALUE ="" DESCRIPTION ="" EXPRESSION ="TO_CHAR( out_DATE_VALUE ,&apos;MONTH&apos; )" EXPRESSIONTYPE ="GENERAL" NAME ="var_MONTH_NAME" PICTURETEXT ="" PORTTYPE ="LOCAL VARIABLE" PRECISION ="20" SCALE ="0"/>
        <TRANSFORMFIELD DATATYPE ="string" DEFAULTVALUE ="" DESCRIPTION ="" EXPRESSION ="TO_INTEGER(TO_CHAR(out_DATE_VALUE,&apos;DDD&apos;))" EXPRESSIONTYPE ="GENERAL" NAME ="var_DAY_OF_YEAR" PICTURETEXT ="" PORTTYPE ="LOCAL VARIABLE" PRECISION ="20" SCALE ="0"/>
        <TRANSFORMFIELD DATATYPE ="string" DEFAULTVALUE ="" DESCRIPTION ="" EXPRESSION ="TO_CHAR(out_DATE_VALUE,&apos;MONTH&apos;)" EXPRESSIONTYPE ="GENERAL" NAME ="var_MONTH_OF_YEAR" PICTURETEXT ="" PORTTYPE ="LOCAL VARIABLE" PRECISION ="20" SCALE ="0"/>
        <TRANSFORMFIELD DATATYPE ="string" DEFAULTVALUE ="" DESCRIPTION ="" EXPRESSION ="TO_CHAR(out_DATE_VALUE,&apos;WW&apos;)" EXPRESSIONTYPE ="GENERAL" NAME ="var_WEEK_OF_YEAR" PICTURETEXT ="" PORTTYPE ="LOCAL VARIABLE" PRECISION ="20" SCALE ="0"/>
        <TRANSFORMFIELD DATATYPE ="string" DEFAULTVALUE ="" DESCRIPTION ="" EXPRESSION ="TO_CHAR(&#xD;&#xA;GET_DATE_PART(&#xD;&#xA;(ADD_TO_DATE(&#xD;&#xA;out_DATE_VALUE, &apos;DD&apos;, 1 )),&apos;DD&apos;))" EXPRESSIONTYPE ="GENERAL" NAME ="var_DAY_OVERALL" PICTURETEXT ="" PORTTYPE ="LOCAL VARIABLE" PRECISION ="20" SCALE ="0"/>
        <TRANSFORMFIELD DATATYPE ="string" DEFAULTVALUE ="" DESCRIPTION ="" EXPRESSION ="IIF(TO_INTEGER(var_WEEK_OF_YEAR)&gt;=53,1,TO_INTEGER(var_WEEK_OF_YEAR)+1)" EXPRESSIONTYPE ="GENERAL" NAME ="var_WEEK_OVERALL" PICTURETEXT ="" PORTTYPE ="LOCAL VARIABLE" PRECISION ="20" SCALE ="0"/>
        <TRANSFORMFIELD DATATYPE ="string" DEFAULTVALUE ="" DESCRIPTION ="" EXPRESSION ="TO_CHAR(&#xD;&#xA;GET_DATE_PART(&#xD;&#xA;(ADD_TO_DATE(&#xD;&#xA;out_DATE_VALUE, &apos;MM&apos;, 1 )),&apos;MM&apos;))" EXPRESSIONTYPE ="GENERAL" NAME ="var_MONTH_OVERALL" PICTURETEXT ="" PORTTYPE ="LOCAL VARIABLE" PRECISION ="20" SCALE ="0"/>
        <TRANSFORMFIELD DATATYPE ="string" DEFAULTVALUE ="" DESCRIPTION ="" EXPRESSION ="TO_CHAR(&#xD;&#xA;GET_DATE_PART(&#xD;&#xA;(ADD_TO_DATE(&#xD;&#xA;out_DATE_VALUE, &apos;YY&apos;, 1 )),&apos;YY&apos;))" EXPRESSIONTYPE ="GENERAL" NAME ="var_YEAR_OVERALL" PICTURETEXT ="" PORTTYPE ="LOCAL VARIABLE" PRECISION ="20" SCALE ="0"/>
        <TRANSFORMFIELD DATATYPE ="string" DEFAULTVALUE ="" DESCRIPTION ="" EXPRESSION ="DECODE(TRUE&#xD;&#xA;,var_DAY_OF_MONTH||&apos;/&apos;||var_MONTH_NUMBER=&apos;01/01&apos;,1&#xD;&#xA;,var_DAY_OF_MONTH||&apos;/&apos;||var_MONTH_NUMBER=&apos;12/31&apos;,1&#xD;&#xA;,var_DAY_OF_MONTH||&apos;/&apos;||var_MONTH_NUMBER=&apos;05/01&apos;,1&#xD;&#xA;,0)" EXPRESSIONTYPE ="GENERAL" NAME ="var_HOLIDAY_INDICATOR" PICTURETEXT ="" PORTTYPE ="LOCAL VARIABLE" PRECISION ="20" SCALE ="0"/>
        <TRANSFORMFIELD DATATYPE ="string" DEFAULTVALUE ="" DESCRIPTION ="" EXPRESSION ="DECODE(TRUE&#xD;&#xA;,var_DAY_OF_MONTH||&apos;/&apos;||var_MONTH_NUMBER!=&apos;01/01&apos;,1&#xD;&#xA;,var_DAY_OF_MONTH||&apos;/&apos;||var_MONTH_NUMBER!=&apos;01/05&apos;,1&#xD;&#xA;,var_DAY_OF_MONTH||&apos;/&apos;||var_MONTH_NUMBER!=&apos;31/12&apos;,1&#xD;&#xA;,0)" EXPRESSIONTYPE ="GENERAL" NAME ="var_WORKDAY_INDICATOR" PICTURETEXT ="" PORTTYPE ="LOCAL VARIABLE" PRECISION ="20" SCALE ="0"/>
        <TRANSFORMFIELD DATATYPE ="string" DEFAULTVALUE ="" DESCRIPTION ="" EXPRESSION ="DECODE(TRUE&#xD;&#xA;,var_DAY_NAME!=&apos;Saturday&apos;,1&#xD;&#xA;,var_DAY_NAME!=&apos;Monday&apos;,1&#xD;&#xA;,0)" EXPRESSIONTYPE ="GENERAL" NAME ="var_WEEKDAY_INDICATOR" PICTURETEXT ="" PORTTYPE ="LOCAL VARIABLE" PRECISION ="20" SCALE ="0"/>
        <TRANSFORMFIELD DATATYPE ="string" DEFAULTVALUE ="" DESCRIPTION ="" EXPRESSION ="DECODE(TRUE&#xD;&#xA;,var_DAY_NAME =&apos;Saturday&apos;,1&#xD;&#xA;,var_DAY_NAME=&apos;Sunday&apos;,1&#xD;&#xA;,0)" EXPRESSIONTYPE ="GENERAL" NAME ="var_WEEKEND_INDICATOR" PICTURETEXT ="" PORTTYPE ="LOCAL VARIABLE" PRECISION ="20" SCALE ="0"/>
        <TRANSFORMFIELD DATATYPE ="string" DEFAULTVALUE ="" DESCRIPTION ="" EXPRESSION ="DECODE(TRUE&#xD;&#xA;,TO_INTEGER(var_MONTH_NUMBER)&gt;=1 AND TO_INTEGER(var_MONTH_NUMBER)&lt;=3,1&#xD;&#xA;,TO_INTEGER(var_MONTH_NUMBER)&gt;=4 AND TO_INTEGER(var_MONTH_NUMBER)&lt;=6,2&#xD;&#xA;,TO_INTEGER(var_MONTH_NUMBER)&gt;=7 AND TO_INTEGER(var_MONTH_NUMBER)&lt;=9,3&#xD;&#xA;,TO_INTEGER(var_MONTH_NUMBER)&gt;=10 AND TO_INTEGER(var_MONTH_NUMBER)&lt;=12,4&#xD;&#xA;)&#xD;&#xA;    " EXPRESSIONTYPE ="GENERAL" NAME ="var_QUARTER_OF_YEAR" PICTURETEXT ="" PORTTYPE ="LOCAL VARIABLE" PRECISION ="20" SCALE ="0"/>
        <TRANSFORMFIELD DATATYPE ="string" DEFAULTVALUE ="" DESCRIPTION ="" EXPRESSION ="DECODE(TRUE&#xD;&#xA;,TO_INTEGER(var_MONTH_NUMBER)&gt;=3   AND TO_INTEGER(var_MONTH_NUMBER)&lt;=5,&apos;SPRING&apos;&#xD;&#xA;,TO_INTEGER(var_MONTH_NUMBER)&gt;=6   AND TO_INTEGER(var_MONTH_NUMBER)&lt;=8,&apos;SUMMER&apos;&#xD;&#xA;,TO_INTEGER(var_MONTH_NUMBER)&gt;=9   AND TO_INTEGER(var_MONTH_NUMBER)&lt;=11,&apos;FALL&apos;&#xD;&#xA;,TO_INTEGER(var_MONTH_NUMBER)=12  OR TO_INTEGER(var_MONTH_NUMBER)&lt;=2,&apos;WINTER&apos;&#xD;&#xA;)&#xD;&#xA;&#xD;&#xA;&#xD;&#xA;    " EXPRESSIONTYPE ="GENERAL" NAME ="var_SEASON" PICTURETEXT ="" PORTTYPE ="LOCAL VARIABLE" PRECISION ="20" SCALE ="0"/>
        <TRANSFORMFIELD DATATYPE ="string" DEFAULTVALUE ="" DESCRIPTION ="" EXPRESSION ="IIF(&#xD;&#xA;out_DATE_VALUE= LAST_DAY(out_DATE_VALUE),1,0)&#xD;&#xA;" EXPRESSIONTYPE ="GENERAL" NAME ="var_LAST_DAY_IN_MONTH" PICTURETEXT ="" PORTTYPE ="LOCAL VARIABLE" PRECISION ="20" SCALE ="0"/>
        <TRANSFORMFIELD DATATYPE ="string" DEFAULTVALUE ="" DESCRIPTION ="" EXPRESSION ="IIF(var_LAST_DAY_IN_MONTH=&apos;1&apos;&#xD;&#xA;,DECODE(TRUE&#xD;&#xA;,var_QUARTER_OF_YEAR=&apos;1&apos; AND var_MONTH_NUMBER=&apos;3&apos;,1&#xD;&#xA;,var_QUARTER_OF_YEAR=&apos;2&apos; AND var_MONTH_NUMBER=&apos;6&apos;,1&#xD;&#xA;,var_QUARTER_OF_YEAR=&apos;3&apos; AND var_MONTH_NUMBER=&apos;9&apos;,1&#xD;&#xA;,var_QUARTER_OF_YEAR=&apos;4&apos; AND var_MONTH_NUMBER=&apos;12&apos;,1&#xD;&#xA;,0)&#xD;&#xA;)" EXPRESSIONTYPE ="GENERAL" NAME ="var_LAST_DAY_IN_QUARTER" PICTURETEXT ="" PORTTYPE ="LOCAL VARIABLE" PRECISION ="20" SCALE ="0"/>
        <TRANSFORMFIELD DATATYPE ="string" DEFAULTVALUE ="" DESCRIPTION ="" EXPRESSION ="IIF(var_LAST_DAY_IN_MONTH=&apos;1&apos; AND var_MONTH_NUMBER=&apos;12&apos;,1,0)" EXPRESSIONTYPE ="GENERAL" NAME ="var_LAST_DAY_IN_YEAR" PICTURETEXT ="" PORTTYPE ="LOCAL VARIABLE" PRECISION ="20" SCALE ="0"/>
        <TRANSFORMFIELD DATATYPE ="date/time" DEFAULTVALUE ="ERROR(&apos;transformation error&apos;)" DESCRIPTION ="" EXPRESSION ="out_DATE_VALUE" EXPRESSIONTYPE ="GENERAL" NAME ="DATE_VALUE" PICTURETEXT ="" PORTTYPE ="OUTPUT" PRECISION ="29" SCALE ="9"/>
        <TRANSFORMFIELD DATATYPE ="string" DEFAULTVALUE ="ERROR(&apos;transformation error&apos;)" DESCRIPTION ="" EXPRESSION ="var_DAY_OF_MONTH" EXPRESSIONTYPE ="GENERAL" NAME ="out_DAY_OF_MONTH" PICTURETEXT ="" PORTTYPE ="OUTPUT" PRECISION ="20" SCALE ="0"/>
        <TRANSFORMFIELD DATATYPE ="string" DEFAULTVALUE ="ERROR(&apos;transformation error&apos;)" DESCRIPTION ="" EXPRESSION ="var_MONTH_NUMBER" EXPRESSIONTYPE ="GENERAL" NAME ="out_MONTH_NUMBER" PICTURETEXT ="" PORTTYPE ="OUTPUT" PRECISION ="20" SCALE ="0"/>
        <TRANSFORMFIELD DATATYPE ="string" DEFAULTVALUE ="ERROR(&apos;transformation error&apos;)" DESCRIPTION ="" EXPRESSION ="var_YEAR_VALUE" EXPRESSIONTYPE ="GENERAL" NAME ="out_YEAR_VALUE" PICTURETEXT ="" PORTTYPE ="OUTPUT" PRECISION ="20" SCALE ="0"/>
        <TRANSFORMFIELD DATATYPE ="string" DEFAULTVALUE ="ERROR(&apos;transformation error&apos;)" DESCRIPTION ="" EXPRESSION ="var_DAY_OF_WEEK" EXPRESSIONTYPE ="GENERAL" NAME ="out_DAY_OF_WEEK" PICTURETEXT ="" PORTTYPE ="OUTPUT" PRECISION ="20" SCALE ="0"/>
        <TRANSFORMFIELD DATATYPE ="string" DEFAULTVALUE ="ERROR(&apos;transformation error&apos;)" DESCRIPTION ="" EXPRESSION ="var_DAY_NAME" EXPRESSIONTYPE ="GENERAL" NAME ="out_DAY_NAME" PICTURETEXT ="" PORTTYPE ="OUTPUT" PRECISION ="20" SCALE ="0"/>
        <TRANSFORMFIELD DATATYPE ="string" DEFAULTVALUE ="ERROR(&apos;transformation error&apos;)" DESCRIPTION ="" EXPRESSION ="var_MONTH_NAME" EXPRESSIONTYPE ="GENERAL" NAME ="out_MONTH_NAME" PICTURETEXT ="" PORTTYPE ="OUTPUT" PRECISION ="20" SCALE ="0"/>
        <TRANSFORMFIELD DATATYPE ="string" DEFAULTVALUE ="ERROR(&apos;transformation error&apos;)" DESCRIPTION ="" EXPRESSION ="var_DAY_OF_YEAR" EXPRESSIONTYPE ="GENERAL" NAME ="out_DAY_OF_YEAR" PICTURETEXT ="" PORTTYPE ="OUTPUT" PRECISION ="20" SCALE ="0"/>
        <TRANSFORMFIELD DATATYPE ="string" DEFAULTVALUE ="ERROR(&apos;transformation error&apos;)" DESCRIPTION ="" EXPRESSION ="var_MONTH_OF_YEAR" EXPRESSIONTYPE ="GENERAL" NAME ="out_MONTH_OF_YEAR" PICTURETEXT ="" PORTTYPE ="OUTPUT" PRECISION ="20" SCALE ="0"/>
        <TRANSFORMFIELD DATATYPE ="string" DEFAULTVALUE ="ERROR(&apos;transformation error&apos;)" DESCRIPTION ="" EXPRESSION ="var_WEEK_OF_YEAR" EXPRESSIONTYPE ="GENERAL" NAME ="out_WEEK_OF_YEAR" PICTURETEXT ="" PORTTYPE ="OUTPUT" PRECISION ="20" SCALE ="0"/>
        <TRANSFORMFIELD DATATYPE ="string" DEFAULTVALUE ="ERROR(&apos;transformation error&apos;)" DESCRIPTION ="" EXPRESSION ="var_DAY_OVERALL" EXPRESSIONTYPE ="GENERAL" NAME ="out_DAY_OVERALL" PICTURETEXT ="" PORTTYPE ="OUTPUT" PRECISION ="20" SCALE ="0"/>
        <TRANSFORMFIELD DATATYPE ="string" DEFAULTVALUE ="ERROR(&apos;transformation error&apos;)" DESCRIPTION ="" EXPRESSION ="var_WEEK_OVERALL" EXPRESSIONTYPE ="GENERAL" NAME ="out_WEEK_OVERALL" PICTURETEXT ="" PORTTYPE ="OUTPUT" PRECISION ="20" SCALE ="0"/>
        <TRANSFORMFIELD DATATYPE ="string" DEFAULTVALUE ="ERROR(&apos;transformation error&apos;)" DESCRIPTION ="" EXPRESSION ="var_MONTH_OVERALL" EXPRESSIONTYPE ="GENERAL" NAME ="out_MONTH_OVERALL" PICTURETEXT ="" PORTTYPE ="OUTPUT" PRECISION ="20" SCALE ="0"/>
        <TRANSFORMFIELD DATATYPE ="string" DEFAULTVALUE ="ERROR(&apos;transformation error&apos;)" DESCRIPTION ="" EXPRESSION ="var_YEAR_OVERALL" EXPRESSIONTYPE ="GENERAL" NAME ="out_YEAR_OVERALL" PICTURETEXT ="" PORTTYPE ="OUTPUT" PRECISION ="20" SCALE ="0"/>
        <TRANSFORMFIELD DATATYPE ="string" DEFAULTVALUE ="ERROR(&apos;transformation error&apos;)" DESCRIPTION ="" EXPRESSION ="var_HOLIDAY_INDICATOR" EXPRESSIONTYPE ="GENERAL" NAME ="out_HOLIDAY_INDICATOR" PICTURETEXT ="" PORTTYPE ="OUTPUT" PRECISION ="20" SCALE ="0"/>
        <TRANSFORMFIELD DATATYPE ="string" DEFAULTVALUE ="ERROR(&apos;transformation error&apos;)" DESCRIPTION ="" EXPRESSION ="var_WORKDAY_INDICATOR" EXPRESSIONTYPE ="GENERAL" NAME ="out_WORKDAY_INDICATOR" PICTURETEXT ="" PORTTYPE ="OUTPUT" PRECISION ="20" SCALE ="0"/>
        <TRANSFORMFIELD DATATYPE ="string" DEFAULTVALUE ="ERROR(&apos;transformation error&apos;)" DESCRIPTION ="" EXPRESSION ="var_WEEKDAY_INDICATOR" EXPRESSIONTYPE ="GENERAL" NAME ="out_WEEKDAY_INDICATOR" PICTURETEXT ="" PORTTYPE ="OUTPUT" PRECISION ="20" SCALE ="0"/>
        <TRANSFORMFIELD DATATYPE ="string" DEFAULTVALUE ="ERROR(&apos;transformation error&apos;)" DESCRIPTION =" " EXPRESSION ="var_WEEKEND_INDICATOR" EXPRESSIONTYPE ="GENERAL" NAME ="out_WEKEEND_INDICATOR" PICTURETEXT ="" PORTTYPE ="OUTPUT" PRECISION ="20" SCALE ="0"/>
        <TRANSFORMFIELD DATATYPE ="string" DEFAULTVALUE ="ERROR(&apos;transformation error&apos;)" DESCRIPTION ="" EXPRESSION ="var_QUARTER_OF_YEAR" EXPRESSIONTYPE ="GENERAL" NAME ="out_QUARTER_OF_YEAR" PICTURETEXT ="" PORTTYPE ="OUTPUT" PRECISION ="20" SCALE ="0"/>
        <TRANSFORMFIELD DATATYPE ="string" DEFAULTVALUE ="ERROR(&apos;transformation error&apos;)" DESCRIPTION ="" EXPRESSION ="var_SEASON" EXPRESSIONTYPE ="GENERAL" NAME ="out_SEASON" PICTURETEXT ="" PORTTYPE ="OUTPUT" PRECISION ="20" SCALE ="0"/>
        <TRANSFORMFIELD DATATYPE ="string" DEFAULTVALUE ="ERROR(&apos;transformation error&apos;)" DESCRIPTION ="" EXPRESSION ="var_LAST_DAY_IN_MONTH" EXPRESSIONTYPE ="GENERAL" NAME ="out_LAST_DAY_IN_MONTH" PICTURETEXT ="" PORTTYPE ="OUTPUT" PRECISION ="20" SCALE ="0"/>
        <TRANSFORMFIELD DATATYPE ="string" DEFAULTVALUE ="ERROR(&apos;transformation error&apos;)" DESCRIPTION ="" EXPRESSION ="var_LAST_DAY_IN_QUARTER" EXPRESSIONTYPE ="GENERAL" NAME ="out_LAST_DAY_IN_QUARTER" PICTURETEXT ="" PORTTYPE ="OUTPUT" PRECISION ="20" SCALE ="0"/>
        <TRANSFORMFIELD DATATYPE ="string" DEFAULTVALUE ="ERROR(&apos;transformation error&apos;)" DESCRIPTION ="" EXPRESSION ="var_LAST_DAY_IN_YEAR" EXPRESSIONTYPE ="GENERAL" NAME ="out_LAST_DAY_IN_YEAR" PICTURETEXT ="" PORTTYPE ="OUTPUT" PRECISION ="20" SCALE ="0"/>
        <TABLEATTRIBUTE NAME ="Tracing Level" VALUE ="Normal"/>
        <METADATAEXTENSION DATATYPE ="STRING" DESCRIPTION ="" DOMAINNAME ="User Defined Metadata Domain" ISCLIENTEDITABLE ="YES" ISCLIENTVISIBLE ="YES" ISREUSABLE ="YES" ISSHAREREAD ="NO" ISSHAREWRITE ="NO" MAXLENGTH ="256" NAME ="Extension" VALUE ="" VENDORNAME ="INFORMATICA"/>
    </TRANSFORMATION>
    <MAPPING DESCRIPTION ="" ISVALID ="YES" NAME ="m_STG_DATES_08" OBJECTVERSION ="1" VERSIONNUMBER ="1">
        <TRANSFORMATION DESCRIPTION ="" NAME ="SQ_dates" OBJECTVERSION ="1" REUSABLE ="NO" TYPE ="Source Qualifier" VERSIONNUMBER ="1">
            <TRANSFORMFIELD DATATYPE ="decimal" DEFAULTVALUE ="" DESCRIPTION ="" NAME ="DATE_ID" PICTURETEXT ="" PORTTYPE ="INPUT/OUTPUT" PRECISION ="7" SCALE ="0"/>
            <TRANSFORMFIELD DATATYPE ="string" DEFAULTVALUE ="" DESCRIPTION ="" NAME ="DATE" PICTURETEXT ="" PORTTYPE ="INPUT/OUTPUT" PRECISION ="10" SCALE ="0"/>
            <TABLEATTRIBUTE NAME ="Sql Query" VALUE =""/>
            <TABLEATTRIBUTE NAME ="User Defined Join" VALUE =""/>
            <TABLEATTRIBUTE NAME ="Source Filter" VALUE =""/>
            <TABLEATTRIBUTE NAME ="Number Of Sorted Ports" VALUE ="0"/>
            <TABLEATTRIBUTE NAME ="Tracing Level" VALUE ="Normal"/>
            <TABLEATTRIBUTE NAME ="Select Distinct" VALUE ="NO"/>
            <TABLEATTRIBUTE NAME ="Is Partitionable" VALUE ="NO"/>
            <TABLEATTRIBUTE NAME ="Pre SQL" VALUE =""/>
            <TABLEATTRIBUTE NAME ="Post SQL" VALUE =""/>
            <TABLEATTRIBUTE NAME ="Output is deterministic" VALUE ="NO"/>
            <TABLEATTRIBUTE NAME ="Output is repeatable" VALUE ="Never"/>
        </TRANSFORMATION>
        <INSTANCE DESCRIPTION ="" INSTANCEID ="1" NAME ="STG_DATES" TRANSFORMATION_NAME ="STG_DATES" TRANSFORMATION_TYPE ="Target Definition" TYPE ="TARGET"/>
        <INSTANCE DBDNAME ="FlatFile" DESCRIPTION ="" INSTANCEID ="2" NAME ="dates" TRANSFORMATION_NAME ="dates" TRANSFORMATION_TYPE ="Source Definition" TYPE ="SOURCE"/>
        <INSTANCE DESCRIPTION ="" INSTANCEID ="3" NAME ="SQ_dates" REUSABLE ="NO" TRANSFORMATION_NAME ="SQ_dates" TRANSFORMATION_TYPE ="Source Qualifier" TYPE ="TRANSFORMATION">
            <ASSOCIATED_SOURCE_INSTANCE NAME ="dates"/>
        </INSTANCE>
        <INSTANCE DESCRIPTION ="" INSTANCEID ="5" NAME ="re_exp_Stg_Dates" REUSABLE ="YES" TRANSFORMATION_NAME ="re_exp_Stg_Dates" TRANSFORMATION_TYPE ="Expression" TYPE ="TRANSFORMATION"/>
        <CONNECTOR FROMFIELD ="DATE_ID" FROMINSTANCE ="re_exp_Stg_Dates" FROMINSTANCETYPE ="Expression" TOFIELD ="DATE_ID_LEGACY" TOINSTANCE ="STG_DATES" TOINSTANCETYPE ="Target Definition"/>
        <CONNECTOR FROMFIELD ="DATE_VALUE" FROMINSTANCE ="re_exp_Stg_Dates" FROMINSTANCETYPE ="Expression" TOFIELD ="DATE_VALUE" TOINSTANCE ="STG_DATES" TOINSTANCETYPE ="Target Definition"/>
        <CONNECTOR FROMFIELD ="out_DAY_OF_MONTH" FROMINSTANCE ="re_exp_Stg_Dates" FROMINSTANCETYPE ="Expression" TOFIELD ="DAY_OF_MONTH" TOINSTANCE ="STG_DATES" TOINSTANCETYPE ="Target Definition"/>
        <CONNECTOR FROMFIELD ="out_MONTH_NUMBER" FROMINSTANCE ="re_exp_Stg_Dates" FROMINSTANCETYPE ="Expression" TOFIELD ="MONTH_NUMBER" TOINSTANCE ="STG_DATES" TOINSTANCETYPE ="Target Definition"/>
        <CONNECTOR FROMFIELD ="out_YEAR_VALUE" FROMINSTANCE ="re_exp_Stg_Dates" FROMINSTANCETYPE ="Expression" TOFIELD ="YEAR_VALUE" TOINSTANCE ="STG_DATES" TOINSTANCETYPE ="Target Definition"/>
        <CONNECTOR FROMFIELD ="out_DAY_OF_WEEK" FROMINSTANCE ="re_exp_Stg_Dates" FROMINSTANCETYPE ="Expression" TOFIELD ="DAY_OF_WEEK" TOINSTANCE ="STG_DATES" TOINSTANCETYPE ="Target Definition"/>
        <CONNECTOR FROMFIELD ="out_DAY_NAME" FROMINSTANCE ="re_exp_Stg_Dates" FROMINSTANCETYPE ="Expression" TOFIELD ="DAY_NAME" TOINSTANCE ="STG_DATES" TOINSTANCETYPE ="Target Definition"/>
        <CONNECTOR FROMFIELD ="out_MONTH_NAME" FROMINSTANCE ="re_exp_Stg_Dates" FROMINSTANCETYPE ="Expression" TOFIELD ="MONTH_NAME" TOINSTANCE ="STG_DATES" TOINSTANCETYPE ="Target Definition"/>
        <CONNECTOR FROMFIELD ="out_DAY_OF_YEAR" FROMINSTANCE ="re_exp_Stg_Dates" FROMINSTANCETYPE ="Expression" TOFIELD ="DAY_OF_YEAR" TOINSTANCE ="STG_DATES" TOINSTANCETYPE ="Target Definition"/>
        <CONNECTOR FROMFIELD ="out_MONTH_OF_YEAR" FROMINSTANCE ="re_exp_Stg_Dates" FROMINSTANCETYPE ="Expression" TOFIELD ="MONTH_OF_YEAR" TOINSTANCE ="STG_DATES" TOINSTANCETYPE ="Target Definition"/>
        <CONNECTOR FROMFIELD ="out_WEEK_OF_YEAR" FROMINSTANCE ="re_exp_Stg_Dates" FROMINSTANCETYPE ="Expression" TOFIELD ="WEEK_OF_YEAR" TOINSTANCE ="STG_DATES" TOINSTANCETYPE ="Target Definition"/>
        <CONNECTOR FROMFIELD ="out_DAY_OVERALL" FROMINSTANCE ="re_exp_Stg_Dates" FROMINSTANCETYPE ="Expression" TOFIELD ="DAY_OVERALL" TOINSTANCE ="STG_DATES" TOINSTANCETYPE ="Target Definition"/>
        <CONNECTOR FROMFIELD ="out_WEEK_OVERALL" FROMINSTANCE ="re_exp_Stg_Dates" FROMINSTANCETYPE ="Expression" TOFIELD ="WEEK_OVERALL" TOINSTANCE ="STG_DATES" TOINSTANCETYPE ="Target Definition"/>
        <CONNECTOR FROMFIELD ="out_MONTH_OVERALL" FROMINSTANCE ="re_exp_Stg_Dates" FROMINSTANCETYPE ="Expression" TOFIELD ="MONTH_OVERALL" TOINSTANCE ="STG_DATES" TOINSTANCETYPE ="Target Definition"/>
        <CONNECTOR FROMFIELD ="out_YEAR_OVERALL" FROMINSTANCE ="re_exp_Stg_Dates" FROMINSTANCETYPE ="Expression" TOFIELD ="YEAR_OVERALL" TOINSTANCE ="STG_DATES" TOINSTANCETYPE ="Target Definition"/>
        <CONNECTOR FROMFIELD ="out_HOLIDAY_INDICATOR" FROMINSTANCE ="re_exp_Stg_Dates" FROMINSTANCETYPE ="Expression" TOFIELD ="HOLIDAY_INDICATOR" TOINSTANCE ="STG_DATES" TOINSTANCETYPE ="Target Definition"/>
        <CONNECTOR FROMFIELD ="out_WORKDAY_INDICATOR" FROMINSTANCE ="re_exp_Stg_Dates" FROMINSTANCETYPE ="Expression" TOFIELD ="WORKDAY_INDICATOR" TOINSTANCE ="STG_DATES" TOINSTANCETYPE ="Target Definition"/>
        <CONNECTOR FROMFIELD ="out_WEEKDAY_INDICATOR" FROMINSTANCE ="re_exp_Stg_Dates" FROMINSTANCETYPE ="Expression" TOFIELD ="WEEKDAY_INDICATOR" TOINSTANCE ="STG_DATES" TOINSTANCETYPE ="Target Definition"/>
        <CONNECTOR FROMFIELD ="out_WEKEEND_INDICATOR" FROMINSTANCE ="re_exp_Stg_Dates" FROMINSTANCETYPE ="Expression" TOFIELD ="WEEKEND_INDICATOR" TOINSTANCE ="STG_DATES" TOINSTANCETYPE ="Target Definition"/>
        <CONNECTOR FROMFIELD ="out_QUARTER_OF_YEAR" FROMINSTANCE ="re_exp_Stg_Dates" FROMINSTANCETYPE ="Expression" TOFIELD ="QUARTER_OF_YEAR" TOINSTANCE ="STG_DATES" TOINSTANCETYPE ="Target Definition"/>
        <CONNECTOR FROMFIELD ="out_SEASON" FROMINSTANCE ="re_exp_Stg_Dates" FROMINSTANCETYPE ="Expression" TOFIELD ="SEASON" TOINSTANCE ="STG_DATES" TOINSTANCETYPE ="Target Definition"/>
        <CONNECTOR FROMFIELD ="out_LAST_DAY_IN_MONTH" FROMINSTANCE ="re_exp_Stg_Dates" FROMINSTANCETYPE ="Expression" TOFIELD ="LAST_DAY_IN_MONTH" TOINSTANCE ="STG_DATES" TOINSTANCETYPE ="Target Definition"/>
        <CONNECTOR FROMFIELD ="out_LAST_DAY_IN_QUARTER" FROMINSTANCE ="re_exp_Stg_Dates" FROMINSTANCETYPE ="Expression" TOFIELD ="LAST_DAY_IN_QUARTER" TOINSTANCE ="STG_DATES" TOINSTANCETYPE ="Target Definition"/>
        <CONNECTOR FROMFIELD ="out_LAST_DAY_IN_YEAR" FROMINSTANCE ="re_exp_Stg_Dates" FROMINSTANCETYPE ="Expression" TOFIELD ="LAST_DAY_IN_YEAR" TOINSTANCE ="STG_DATES" TOINSTANCETYPE ="Target Definition"/>
        <CONNECTOR FROMFIELD ="DATE_ID" FROMINSTANCE ="dates" FROMINSTANCETYPE ="Source Definition" TOFIELD ="DATE_ID" TOINSTANCE ="SQ_dates" TOINSTANCETYPE ="Source Qualifier"/>
        <CONNECTOR FROMFIELD ="DATE" FROMINSTANCE ="dates" FROMINSTANCETYPE ="Source Definition" TOFIELD ="DATE" TOINSTANCE ="SQ_dates" TOINSTANCETYPE ="Source Qualifier"/>
        <CONNECTOR FROMFIELD ="DATE_ID" FROMINSTANCE ="SQ_dates" FROMINSTANCETYPE ="Source Qualifier" TOFIELD ="DATE_ID" TOINSTANCE ="re_exp_Stg_Dates" TOINSTANCETYPE ="Expression"/>
        <CONNECTOR FROMFIELD ="DATE" FROMINSTANCE ="SQ_dates" FROMINSTANCETYPE ="Source Qualifier" TOFIELD ="DATE" TOINSTANCE ="re_exp_Stg_Dates" TOINSTANCETYPE ="Expression"/>
        <TARGETLOADORDER ORDER ="1" TARGETINSTANCE ="STG_DATES"/>
        <ERPINFO/>
    </MAPPING>
</FOLDER>
</REPOSITORY>
</POWERMART>